aido_client/__init__.py
aido_client/callbacks/__init__.py
aido_client/callbacks/base.py
aido_client/callbacks/shared.py
aido_client/chains/__init__.py
aido_client/chains/base.py
aido_client/chains/llm.py
aido_client/client.py
aido_client/llms/__init__.py
aido_client/llms/base.py
aido_client/llms/openai.py
aido_client/prompts/__init__.py
aido_client/prompts/base.py
aido_client/prompts/chat.py
aido_client/prompts/prompt.py
aido_client/schemas/__init__.py
aido_client/schemas/schema.py
aido_client/utils/__init__.py
aido_client/utils/formatting.py
aido_client/utils/input.py
aido_client/utils/utils.py
aido_client-0.1.3.dist-info/METADATA
aido_client-0.1.3.dist-info/WHEEL
aido_client-0.1.3.dist-info/RECORD
