Metadata-Version: 2.1
Name: aido-client
Version: 0.1.3
Summary: 
Author: ericjiang
Author-email: my.cheng@msn.com
Requires-Python: >=3.7,<4.0
Classifier: Programming Language :: Python :: 3
Classifier: Programming Language :: Python :: 3.7
Classifier: Programming Language :: Python :: 3.8
Classifier: Programming Language :: Python :: 3.9
Classifier: Programming Language :: Python :: 3.10
Classifier: Programming Language :: Python :: 3.11
Classifier: Programming Language :: Python :: 3.12
Requires-Dist: jinja2 (>=3.1.3,<4.0.0)
Requires-Dist: openai (>=1.12.0,<2.0.0)
Requires-Dist: pydantic (==1.10.12)
Requires-Dist: requests (>=2.31.0,<3.0.0)
Requires-Dist: transformers (>=4.28.1,<5.0.0)
